{
  "ticker": "QQQ",
  "expiry_date": "2026-07-14",
  "snapshot_date": "2026-07-14",
  "snapshot_sequence": 1,
  "snapshot_label": "Jul 14, 2026 (1)",
  "days_to_expiry": 0,
  "expiry_type": "daily",
  "expiration_cadence": "daily",
  "underlying_price": 721.695,
  "total_call_oi": 120409,
  "total_put_oi": 242999,
  "total_oi": 363408,
  "gex_total": 549961408,
  "max_pain": 715,
  "expected_move": 5.6,
  "source": "Yahoo Finance via yahoo-finance2",
  "collected_at": "2026-07-14T15:24:30.360Z",
  "rows": [
    {
      "strike": 495,
      "call_symbol": "",
      "put_symbol": "QQQ260714P00495000",
      "call_oi": 0,
      "put_oi": 765,
      "call_volume": 0,
      "put_volume": 6,
      "call_iv": 0,
      "put_iv": 2.1250046874999997,
      "call_bid": 0,
      "put_bid": 0,
      "call_ask": 0,
      "put_ask": 0.01,
      "call_last": 0,
      "put_last": 0.01,
      "call_gex": 0,
      "put_gex": -12753,
      "total_gex": -12753,
      "volume": 6,
      "probability": 1.85
    },
    {
      "strike": 500,
      "call_symbol": "",
      "put_symbol": "QQQ260714P00500000",
      "call_oi": 0,
      "put_oi": 1,
      "call_volume": 0,
      "put_volume": 0,
      "call_iv": 0,
      "put_iv": 2.156254609375,
      "call_bid": 0,
      "put_bid": 0,
      "call_ask": 0,
      "put_ask": 0.01,
      "call_last": 0,
      "put_last": 0.01,
      "call_gex": 0,
      "put_gex": -22,
      "total_gex": -22,
      "volume": 0,
      "probability": 2.46
    },
    {
      "strike": 505,
      "call_symbol": "QQQ260714C00505000",
      "put_symbol": "",
      "call_oi": 8,
      "put_oi": 0,
      "call_volume": 2,
      "put_volume": 0,
      "call_iv": 0.000010000000000000003,
      "put_iv": 0,
      "call_bid": 211.59,
      "put_bid": 0,
      "call_ask": 215.06,
      "put_ask": 0,
      "call_last": 213,
      "put_last": 0,
      "call_gex": 0,
      "put_gex": 0,
      "total_gex": 0,
      "volume": 2,
      "probability": 0
    },
    {
      "strike": 515,
      "call_symbol": "",
      "put_symbol": "QQQ260714P00515000",
      "call_oi": 0,
      "put_oi": 15,
      "call_volume": 0,
      "put_volume": 0,
      "call_iv": 0,
      "put_iv": 1.984375078125,
      "call_bid": 0,
      "put_bid": 0,
      "call_ask": 0,
      "put_ask": 0.01,
      "call_last": 0,
      "put_last": 0.01,
      "call_gex": 0,
      "put_gex": -323,
      "total_gex": -323,
      "volume": 0,
      "probability": 2.23
    },
    {
      "strike": 520,
      "call_symbol": "",
      "put_symbol": "QQQ260714P00520000",
      "call_oi": 0,
      "put_oi": 3,
      "call_volume": 0,
      "put_volume": 1,
      "call_iv": 0,
      "put_iv": 1.8125009374999999,
      "call_bid": 0,
      "put_bid": 0,
      "call_ask": 0,
      "put_ask": 0.01,
      "call_last": 0,
      "put_last": 0.06,
      "call_gex": 0,
      "put_gex": -41,
      "total_gex": -41,
      "volume": 1,
      "probability": 1.3
    },
    {
      "strike": 525,
      "call_symbol": "QQQ260714C00525000",
      "put_symbol": "QQQ260714P00525000",
      "call_oi": 0,
      "put_oi": 6152,
      "call_volume": 2,
      "put_volume": 2,
      "call_iv": 0.000010000000000000003,
      "put_iv": 1.78125109375,
      "call_bid": 191.37,
      "put_bid": 0,
      "call_ask": 195.28,
      "put_ask": 0.01,
      "call_last": 192.09,
      "put_last": 0.01,
      "call_gex": 0,
      "put_gex": 0,
      "total_gex": 0,
      "volume": 4,
      "probability": 0
    },
    {
      "strike": 530,
      "call_symbol": "",
      "put_symbol": "QQQ260714P00530000",
      "call_oi": 0,
      "put_oi": 7501,
      "call_volume": 0,
      "put_volume": 1,
      "call_iv": 0,
      "put_iv": 1.8281258593749998,
      "call_bid": 0,
      "put_bid": 0,
      "call_ask": 0,
      "put_ask": 0.01,
      "call_last": 0,
      "put_last": 0.01,
      "call_gex": 0,
      "put_gex": -166362,
      "total_gex": -166362,
      "volume": 1,
      "probability": 2.12
    },
    {
      "strike": 535,
      "call_symbol": "",
      "put_symbol": "QQQ260714P00535000",
      "call_oi": 0,
      "put_oi": 7501,
      "call_volume": 0,
      "put_volume": 2,
      "call_iv": 0,
      "put_iv": 1.6875015625,
      "call_bid": 0,
      "put_bid": 0,
      "call_ask": 0,
      "put_ask": 0.01,
      "call_last": 0,
      "put_last": 0.01,
      "call_gex": 0,
      "put_gex": -116529,
      "total_gex": -116529,
      "volume": 2,
      "probability": 1.37
    },
    {
      "strike": 540,
      "call_symbol": "QQQ260714C00540000",
      "put_symbol": "QQQ260714P00540000",
      "call_oi": 0,
      "put_oi": 25007,
      "call_volume": 2,
      "put_volume": 7,
      "call_iv": 0.000010000000000000003,
      "put_iv": 1.71875140625,
      "call_bid": 176.41,
      "put_bid": 0,
      "call_ask": 179.72,
      "put_ask": 0.01,
      "call_last": 177.09,
      "put_last": 0.02,
      "call_gex": 0,
      "put_gex": -9,
      "total_gex": -9,
      "volume": 9,
      "probability": 0
    },
    {
      "strike": 550,
      "call_symbol": "",
      "put_symbol": "QQQ260714P00550000",
      "call_oi": 0,
      "put_oi": 4533,
      "call_volume": 0,
      "put_volume": 3763,
      "call_iv": 0,
      "put_iv": 1.5312523437499999,
      "call_bid": 0,
      "put_bid": 0,
      "call_ask": 0,
      "put_ask": 0.01,
      "call_last": 0,
      "put_last": 0.02,
      "call_gex": 0,
      "put_gex": -69069,
      "total_gex": -69069,
      "volume": 3763,
      "probability": 1.22
    },
    {
      "strike": 555,
      "call_symbol": "",
      "put_symbol": "QQQ260714P00555000",
      "call_oi": 0,
      "put_oi": 1072,
      "call_volume": 0,
      "put_volume": 1068,
      "call_iv": 0,
      "put_iv": 1.5625021874999998,
      "call_bid": 0,
      "put_bid": 0,
      "call_ask": 0,
      "put_ask": 0.01,
      "call_last": 0,
      "put_last": 0.01,
      "call_gex": 0,
      "put_gex": -24296,
      "total_gex": -24296,
      "volume": 1068,
      "probability": 1.85
    },
    {
      "strike": 560,
      "call_symbol": "",
      "put_symbol": "QQQ260714P00560000",
      "call_oi": 0,
      "put_oi": 20657,
      "call_volume": 0,
      "put_volume": 20551,
      "call_iv": 0,
      "put_iv": 1.4375028125,
      "call_bid": 0,
      "put_bid": 0,
      "call_ask": 0,
      "put_ask": 0.01,
      "call_last": 0,
      "put_last": 0.01,
      "call_gex": 0,
      "put_gex": -326009,
      "total_gex": -326009,
      "volume": 20551,
      "probability": 1.19
    },
    {
      "strike": 565,
      "call_symbol": "",
      "put_symbol": "QQQ260714P00565000",
      "call_oi": 0,
      "put_oi": 330,
      "call_volume": 0,
      "put_volume": 325,
      "call_iv": 0,
      "put_iv": 1.46875265625,
      "call_bid": 0,
      "put_bid": 0,
      "call_ask": 0,
      "put_ask": 0.01,
      "call_last": 0,
      "put_last": 0.01,
      "call_gex": 0,
      "put_gex": -7956,
      "total_gex": -7956,
      "volume": 325,
      "probability": 1.85
    },
    {
      "strike": 570,
      "call_symbol": "QQQ260714C00570000",
      "put_symbol": "QQQ260714P00570000",
      "call_oi": 7,
      "put_oi": 30,
      "call_volume": 7,
      "put_volume": 2,
      "call_iv": 0.000010000000000000003,
      "put_iv": 1.3437532812499997,
      "call_bid": 146.35,
      "put_bid": 0,
      "call_ask": 149.72,
      "put_ask": 0.01,
      "call_last": 145.91,
      "put_last": 0.01,
      "call_gex": 0,
      "put_gex": 0,
      "total_gex": 0,
      "volume": 9,
      "probability": 0
    },
    {
      "strike": 575,
      "call_symbol": "",
      "put_symbol": "QQQ260714P00575000",
      "call_oi": 0,
      "put_oi": 48,
      "call_volume": 0,
      "put_volume": 43,
      "call_iv": 0,
      "put_iv": 1.3125034374999998,
      "call_bid": 0,
      "put_bid": 0,
      "call_ask": 0,
      "put_ask": 0.01,
      "call_last": 0,
      "put_last": 0.03,
      "call_gex": 0,
      "put_gex": -878,
      "total_gex": -878,
      "volume": 43,
      "probability": 1.26
    },
    {
      "strike": 580,
      "call_symbol": "",
      "put_symbol": "QQQ260714P00580000",
      "call_oi": 0,
      "put_oi": 755,
      "call_volume": 0,
      "put_volume": 748,
      "call_iv": 0,
      "put_iv": 1.2500037499999999,
      "call_bid": 0,
      "put_bid": 0,
      "call_ask": 0,
      "put_ask": 0.01,
      "call_last": 0,
      "put_last": 0.01,
      "call_gex": 0,
      "put_gex": -12789,
      "total_gex": -12789,
      "volume": 748,
      "probability": 1.11
    },
    {
      "strike": 585,
      "call_symbol": "",
      "put_symbol": "QQQ260714P00585000",
      "call_oi": 0,
      "put_oi": 168,
      "call_volume": 0,
      "put_volume": 129,
      "call_iv": 0,
      "put_iv": 1.21875390625,
      "call_bid": 0,
      "put_bid": 0,
      "call_ask": 0,
      "put_ask": 0.01,
      "call_last": 0,
      "put_last": 0.01,
      "call_gex": 0,
      "put_gex": -3208,
      "total_gex": -3208,
      "volume": 129,
      "probability": 1.22
    },
    {
      "strike": 590,
      "call_symbol": "",
      "put_symbol": "QQQ260714P00590000",
      "call_oi": 0,
      "put_oi": 136,
      "call_volume": 0,
      "put_volume": 93,
      "call_iv": 0,
      "put_iv": 1.15625421875,
      "call_bid": 0,
      "put_bid": 0,
      "call_ask": 0,
      "put_ask": 0.01,
      "call_last": 0,
      "put_last": 0.01,
      "call_gex": 0,
      "put_gex": -2385,
      "total_gex": -2385,
      "volume": 93,
      "probability": 1.06
    },
    {
      "strike": 595,
      "call_symbol": "",
      "put_symbol": "QQQ260714P00595000",
      "call_oi": 0,
      "put_oi": 332,
      "call_volume": 0,
      "put_volume": 229,
      "call_iv": 0,
      "put_iv": 1.125004375,
      "call_bid": 0,
      "put_bid": 0,
      "call_ask": 0,
      "put_ask": 0.01,
      "call_last": 0,
      "put_last": 0.01,
      "call_gex": 0,
      "put_gex": -6625,
      "total_gex": -6625,
      "volume": 229,
      "probability": 1.17
    },
    {
      "strike": 600,
      "call_symbol": "QQQ260714C00600000",
      "put_symbol": "QQQ260714P00600000",
      "call_oi": 40,
      "put_oi": 453,
      "call_volume": 2,
      "put_volume": 537,
      "call_iv": 0.000010000000000000003,
      "put_iv": 1.0625046875000002,
      "call_bid": 116.33,
      "put_bid": 0,
      "call_ask": 118.98,
      "put_ask": 0.01,
      "call_last": 118.86,
      "put_last": 0.01,
      "call_gex": 0,
      "put_gex": 0,
      "total_gex": 0,
      "volume": 539,
      "probability": 0
    },
    {
      "strike": 605,
      "call_symbol": "",
      "put_symbol": "QQQ260714P00605000",
      "call_oi": 0,
      "put_oi": 863,
      "call_volume": 0,
      "put_volume": 400,
      "call_iv": 0,
      "put_iv": 1.0312548437500002,
      "call_bid": 0,
      "put_bid": 0,
      "call_ask": 0,
      "put_ask": 0.01,
      "call_last": 0,
      "put_last": 0.01,
      "call_gex": 0,
      "put_gex": -17999,
      "total_gex": -17999,
      "volume": 400,
      "probability": 1.13
    },
    {
      "strike": 610,
      "call_symbol": "",
      "put_symbol": "QQQ260714P00610000",
      "call_oi": 0,
      "put_oi": 3632,
      "call_volume": 0,
      "put_volume": 18,
      "call_iv": 0,
      "put_iv": 0.9687503125,
      "call_bid": 0,
      "put_bid": 0,
      "call_ask": 0,
      "put_ask": 0.01,
      "call_last": 0,
      "put_last": 0.01,
      "call_gex": 0,
      "put_gex": -67942,
      "total_gex": -67942,
      "volume": 18,
      "probability": 0.95
    },
    {
      "strike": 615,
      "call_symbol": "",
      "put_symbol": "QQQ260714P00615000",
      "call_oi": 0,
      "put_oi": 555,
      "call_volume": 0,
      "put_volume": 518,
      "call_iv": 0,
      "put_iv": 0.937500625,
      "call_bid": 0,
      "put_bid": 0,
      "call_ask": 0,
      "put_ask": 0.01,
      "call_last": 0,
      "put_last": 0.01,
      "call_gex": 0,
      "put_gex": -12091,
      "total_gex": -12091,
      "volume": 518,
      "probability": 1.07
    },
    {
      "strike": 620,
      "call_symbol": "QQQ260714C00620000",
      "put_symbol": "QQQ260714P00620000",
      "call_oi": 5,
      "put_oi": 1090,
      "call_volume": 0,
      "put_volume": 20,
      "call_iv": 0.000010000000000000003,
      "put_iv": 0.9062509375,
      "call_bid": 96.41,
      "put_bid": 0,
      "call_ask": 100.26,
      "put_ask": 0.01,
      "call_last": 98.76,
      "put_last": 0.01,
      "call_gex": 0,
      "put_gex": 0,
      "total_gex": 0,
      "volume": 20,
      "probability": 0
    },
    {
      "strike": 625,
      "call_symbol": "QQQ260714C00625000",
      "put_symbol": "QQQ260714P00625000",
      "call_oi": 1,
      "put_oi": 162,
      "call_volume": 0,
      "put_volume": 160,
      "call_iv": 0.000010000000000000003,
      "put_iv": 0.8437515624999999,
      "call_bid": 91.58,
      "put_bid": 0,
      "call_ask": 95.15,
      "put_ask": 0.01,
      "call_last": 93.32,
      "put_last": 0.01,
      "call_gex": 0,
      "put_gex": 0,
      "total_gex": 0,
      "volume": 160,
      "probability": 0
    },
    {
      "strike": 630,
      "call_symbol": "QQQ260714C00630000",
      "put_symbol": "QQQ260714P00630000",
      "call_oi": 0,
      "put_oi": 2218,
      "call_volume": 9,
      "put_volume": 995,
      "call_iv": 0.000010000000000000003,
      "put_iv": 0.8125018749999999,
      "call_bid": 86.59,
      "put_bid": 0,
      "call_ask": 90.14,
      "put_ask": 0.01,
      "call_last": 81,
      "put_last": 0.02,
      "call_gex": 0,
      "put_gex": 0,
      "total_gex": 0,
      "volume": 1004,
      "probability": 0
    },
    {
      "strike": 635,
      "call_symbol": "",
      "put_symbol": "QQQ260714P00635000",
      "call_oi": 0,
      "put_oi": 531,
      "call_volume": 0,
      "put_volume": 306,
      "call_iv": 0,
      "put_iv": 0.7656273437500001,
      "call_bid": 0,
      "put_bid": 0,
      "call_ask": 0,
      "put_ask": 0.01,
      "call_last": 0,
      "put_last": 0.02,
      "call_gex": 0,
      "put_gex": -14827,
      "total_gex": -14827,
      "volume": 306,
      "probability": 1.12
    },
    {
      "strike": 640,
      "call_symbol": "",
      "put_symbol": "QQQ260714P00640000",
      "call_oi": 0,
      "put_oi": 876,
      "call_volume": 0,
      "put_volume": 11,
      "call_iv": 0,
      "put_iv": 0.7187528125,
      "call_bid": 0,
      "put_bid": 0,
      "call_ask": 0,
      "put_ask": 0.01,
      "call_last": 0,
      "put_last": 0.01,
      "call_gex": 0,
      "put_gex": -25184,
      "total_gex": -25184,
      "volume": 11,
      "probability": 1.08
    },
    {
      "strike": 645,
      "call_symbol": "",
      "put_symbol": "QQQ260714P00645000",
      "call_oi": 0,
      "put_oi": 678,
      "call_volume": 0,
      "put_volume": 1,
      "call_iv": 0,
      "put_iv": 0.6718782812500002,
      "call_bid": 0,
      "put_bid": 0,
      "call_ask": 0,
      "put_ask": 0.01,
      "call_last": 0,
      "put_last": 0.01,
      "call_gex": 0,
      "put_gex": -20055,
      "total_gex": -20055,
      "volume": 1,
      "probability": 1.04
    },
    {
      "strike": 650,
      "call_symbol": "QQQ260714C00650000",
      "put_symbol": "QQQ260714P00650000",
      "call_oi": 1,
      "put_oi": 1952,
      "call_volume": 0,
      "put_volume": 63,
      "call_iv": 0.000010000000000000003,
      "put_iv": 0.6250037500000001,
      "call_bid": 66.59,
      "put_bid": 0,
      "call_ask": 69.7,
      "put_ask": 0.01,
      "call_last": 60.95,
      "put_last": 0.01,
      "call_gex": 0,
      "put_gex": 0,
      "total_gex": 0,
      "volume": 63,
      "probability": 0
    },
    {
      "strike": 655,
      "call_symbol": "QQQ260714C00655000",
      "put_symbol": "QQQ260714P00655000",
      "call_oi": 2,
      "put_oi": 3260,
      "call_volume": 1,
      "put_volume": 164,
      "call_iv": 0.000010000000000000003,
      "put_iv": 0.5937540625000001,
      "call_bid": 61.59,
      "put_bid": 0,
      "call_ask": 65.13,
      "put_ask": 0.01,
      "call_last": 63.95,
      "put_last": 0.01,
      "call_gex": 0,
      "put_gex": 0,
      "total_gex": 0,
      "volume": 165,
      "probability": 0
    },
    {
      "strike": 660,
      "call_symbol": "",
      "put_symbol": "QQQ260714P00660000",
      "call_oi": 0,
      "put_oi": 2189,
      "call_volume": 0,
      "put_volume": 1019,
      "call_iv": 0,
      "put_iv": 0.5468795312500001,
      "call_bid": 0,
      "put_bid": 0,
      "call_ask": 0,
      "put_ask": 0.01,
      "call_last": 0,
      "put_last": 0.01,
      "call_gex": 0,
      "put_gex": -88476,
      "total_gex": -88476,
      "volume": 1019,
      "probability": 1.16
    },
    {
      "strike": 665,
      "call_symbol": "QQQ260714C00665000",
      "put_symbol": "QQQ260714P00665000",
      "call_oi": 1,
      "put_oi": 3477,
      "call_volume": 3,
      "put_volume": 904,
      "call_iv": 0.000010000000000000003,
      "put_iv": 0.500005,
      "call_bid": 52.31,
      "put_bid": 0,
      "call_ask": 55.24,
      "put_ask": 0.01,
      "call_last": 54.05,
      "put_last": 0.01,
      "call_gex": 0,
      "put_gex": 0,
      "total_gex": 0,
      "volume": 907,
      "probability": 0
    },
    {
      "strike": 668,
      "call_symbol": "",
      "put_symbol": "QQQ260714P00668000",
      "call_oi": 0,
      "put_oi": 871,
      "call_volume": 0,
      "put_volume": 1426,
      "call_iv": 0,
      "put_iv": 0.507817421875,
      "call_bid": 0,
      "put_bid": 0,
      "call_ask": 0,
      "put_ask": 0.01,
      "call_last": 0,
      "put_last": 0.01,
      "call_gex": 0,
      "put_gex": -65180,
      "total_gex": -65180,
      "volume": 1426,
      "probability": 1.99
    },
    {
      "strike": 669,
      "call_symbol": "",
      "put_symbol": "QQQ260714P00669000",
      "call_oi": 0,
      "put_oi": 783,
      "call_volume": 0,
      "put_volume": 1582,
      "call_iv": 0,
      "put_iv": 0.500005,
      "call_bid": 0,
      "put_bid": 0,
      "call_ask": 0,
      "put_ask": 0.01,
      "call_last": 0,
      "put_last": 0.01,
      "call_gex": 0,
      "put_gex": -61061,
      "total_gex": -61061,
      "volume": 1582,
      "probability": 2.04
    },
    {
      "strike": 670,
      "call_symbol": "QQQ260714C00670000",
      "put_symbol": "QQQ260714P00670000",
      "call_oi": 82,
      "put_oi": 2234,
      "call_volume": 108,
      "put_volume": 2469,
      "call_iv": 0.000010000000000000003,
      "put_iv": 0.49219257812500006,
      "call_bid": 46.56,
      "put_bid": 0,
      "call_ask": 49.9,
      "put_ask": 0.01,
      "call_last": 48.13,
      "put_last": 0.01,
      "call_gex": 0,
      "put_gex": -3,
      "total_gex": -3,
      "volume": 2577,
      "probability": 0
    },
    {
      "strike": 671,
      "call_symbol": "",
      "put_symbol": "QQQ260714P00671000",
      "call_oi": 0,
      "put_oi": 213,
      "call_volume": 0,
      "put_volume": 2072,
      "call_iv": 0,
      "put_iv": 0.48438015625,
      "call_bid": 0,
      "put_bid": 0,
      "call_ask": 0,
      "put_ask": 0.01,
      "call_last": 0,
      "put_last": 0.01,
      "call_gex": 0,
      "put_gex": -18092,
      "total_gex": -18092,
      "volume": 2072,
      "probability": 2.15
    },
    {
      "strike": 672,
      "call_symbol": "",
      "put_symbol": "QQQ260714P00672000",
      "call_oi": 0,
      "put_oi": 450,
      "call_volume": 0,
      "put_volume": 2809,
      "call_iv": 0,
      "put_iv": 0.4687553125,
      "call_bid": 0,
      "put_bid": 0,
      "call_ask": 0,
      "put_ask": 0.01,
      "call_last": 0,
      "put_last": 0.01,
      "call_gex": 0,
      "put_gex": -35736,
      "total_gex": -35736,
      "volume": 2809,
      "probability": 1.95
    },
    {
      "strike": 673,
      "call_symbol": "",
      "put_symbol": "QQQ260714P00673000",
      "call_oi": 0,
      "put_oi": 433,
      "call_volume": 0,
      "put_volume": 1773,
      "call_iv": 0,
      "put_iv": 0.46094289062500005,
      "call_bid": 0,
      "put_bid": 0,
      "call_ask": 0,
      "put_ask": 0.01,
      "call_last": 0,
      "put_last": 0.01,
      "call_gex": 0,
      "put_gex": -35949,
      "total_gex": -35949,
      "volume": 1773,
      "probability": 2
    },
    {
      "strike": 674,
      "call_symbol": "",
      "put_symbol": "QQQ260714P00674000",
      "call_oi": 0,
      "put_oi": 952,
      "call_volume": 0,
      "put_volume": 3829,
      "call_iv": 0,
      "put_iv": 0.45313046875,
      "call_bid": 0,
      "put_bid": 0,
      "call_ask": 0,
      "put_ask": 0.01,
      "call_last": 0,
      "put_last": 0.01,
      "call_gex": 0,
      "put_gex": -82724,
      "total_gex": -82724,
      "volume": 3829,
      "probability": 2.06
    },
    {
      "strike": 675,
      "call_symbol": "QQQ260714C00675000",
      "put_symbol": "QQQ260714P00675000",
      "call_oi": 6,
      "put_oi": 3382,
      "call_volume": 3,
      "put_volume": 5196,
      "call_iv": 0.000010000000000000003,
      "put_iv": 0.476567734375,
      "call_bid": 41.42,
      "put_bid": 0,
      "call_ask": 44.73,
      "put_ask": 0.02,
      "call_last": 43.3,
      "put_last": 0.01,
      "call_gex": 0,
      "put_gex": -39,
      "total_gex": -39,
      "volume": 5199,
      "probability": 0
    },
    {
      "strike": 676,
      "call_symbol": "",
      "put_symbol": "QQQ260714P00676000",
      "call_oi": 0,
      "put_oi": 1656,
      "call_volume": 0,
      "put_volume": 2906,
      "call_iv": 0,
      "put_iv": 0.437505625,
      "call_bid": 0,
      "put_bid": 0,
      "call_ask": 0,
      "put_ask": 0.01,
      "call_last": 0,
      "put_last": 0.01,
      "call_gex": 0,
      "put_gex": -158204,
      "total_gex": -158204,
      "volume": 2906,
      "probability": 2.19
    },
    {
      "strike": 677,
      "call_symbol": "QQQ260714C00677000",
      "put_symbol": "QQQ260714P00677000",
      "call_oi": 1,
      "put_oi": 465,
      "call_volume": 7,
      "put_volume": 2010,
      "call_iv": 0.000010000000000000003,
      "put_iv": 0.42969320312500003,
      "call_bid": 41.18,
      "put_bid": 0,
      "call_ask": 42.64,
      "put_ask": 0.01,
      "call_last": 41.95,
      "put_last": 0.01,
      "call_gex": 0,
      "put_gex": -1,
      "total_gex": -1,
      "volume": 2017,
      "probability": 0
    },
    {
      "strike": 678,
      "call_symbol": "",
      "put_symbol": "QQQ260714P00678000",
      "call_oi": 0,
      "put_oi": 1198,
      "call_volume": 0,
      "put_volume": 2135,
      "call_iv": 0,
      "put_iv": 0.42188078125,
      "call_bid": 0,
      "put_bid": 0,
      "call_ask": 0,
      "put_ask": 0.01,
      "call_last": 0,
      "put_last": 0.01,
      "call_gex": 0,
      "put_gex": -126481,
      "total_gex": -126481,
      "volume": 2135,
      "probability": 2.33
    },
    {
      "strike": 679,
      "call_symbol": "",
      "put_symbol": "QQQ260714P00679000",
      "call_oi": 0,
      "put_oi": 789,
      "call_volume": 0,
      "put_volume": 2706,
      "call_iv": 0,
      "put_iv": 0.4062559375,
      "call_bid": 0,
      "put_bid": 0,
      "call_ask": 0,
      "put_ask": 0.01,
      "call_last": 0,
      "put_last": 0.01,
      "call_gex": 0,
      "put_gex": -77394,
      "total_gex": -77394,
      "volume": 2706,
      "probability": 2.09
    },
    {
      "strike": 680,
      "call_symbol": "QQQ260714C00680000",
      "put_symbol": "QQQ260714P00680000",
      "call_oi": 77,
      "put_oi": 3583,
      "call_volume": 75,
      "put_volume": 2562,
      "call_iv": 0.000010000000000000003,
      "put_iv": 0.398443515625,
      "call_bid": 36.5,
      "put_bid": 0,
      "call_ask": 39.72,
      "put_ask": 0.01,
      "call_last": 37.8,
      "put_last": 0.01,
      "call_gex": 0,
      "put_gex": -7,
      "total_gex": -7,
      "volume": 2637,
      "probability": 0
    },
    {
      "strike": 681,
      "call_symbol": "",
      "put_symbol": "QQQ260714P00681000",
      "call_oi": 0,
      "put_oi": 311,
      "call_volume": 0,
      "put_volume": 3204,
      "call_iv": 0,
      "put_iv": 0.42188078125,
      "call_bid": 0,
      "put_bid": 0.01,
      "call_ask": 0,
      "put_ask": 0.02,
      "call_last": 0,
      "put_last": 0.02,
      "call_gex": 0,
      "put_gex": -54049,
      "total_gex": -54049,
      "volume": 3204,
      "probability": 3.84
    },
    {
      "strike": 682,
      "call_symbol": "",
      "put_symbol": "QQQ260714P00682000",
      "call_oi": 0,
      "put_oi": 770,
      "call_volume": 0,
      "put_volume": 2168,
      "call_iv": 0,
      "put_iv": 0.4101621484375,
      "call_bid": 0,
      "put_bid": 0.01,
      "call_ask": 0,
      "put_ask": 0.02,
      "call_last": 0,
      "put_last": 0.02,
      "call_gex": 0,
      "put_gex": -134710,
      "total_gex": -134710,
      "volume": 2168,
      "probability": 3.76
    },
    {
      "strike": 683,
      "call_symbol": "",
      "put_symbol": "QQQ260714P00683000",
      "call_oi": 0,
      "put_oi": 1315,
      "call_volume": 0,
      "put_volume": 4686,
      "call_iv": 0,
      "put_iv": 0.4023497265625,
      "call_bid": 0,
      "put_bid": 0.01,
      "call_ask": 0,
      "put_ask": 0.02,
      "call_last": 0,
      "put_last": 0.01,
      "call_gex": 0,
      "put_gex": -244337,
      "total_gex": -244337,
      "volume": 4686,
      "probability": 3.91
    },
    {
      "strike": 684,
      "call_symbol": "",
      "put_symbol": "QQQ260714P00684000",
      "call_oi": 0,
      "put_oi": 619,
      "call_volume": 0,
      "put_volume": 658,
      "call_iv": 0,
      "put_iv": 0.39063109375,
      "call_bid": 0,
      "put_bid": 0.01,
      "call_ask": 0,
      "put_ask": 0.02,
      "call_last": 0,
      "put_last": 0.02,
      "call_gex": 0,
      "put_gex": -115893,
      "total_gex": -115893,
      "volume": 658,
      "probability": 3.83
    },
    {
      "strike": 685,
      "call_symbol": "QQQ260714C00685000",
      "put_symbol": "QQQ260714P00685000",
      "call_oi": 27,
      "put_oi": 6080,
      "call_volume": 37,
      "put_volume": 2568,
      "call_iv": 0.000010000000000000003,
      "put_iv": 0.38281867187499996,
      "call_bid": 31.58,
      "put_bid": 0.01,
      "call_ask": 33.47,
      "put_ask": 0.02,
      "call_last": 33.14,
      "put_last": 0.02,
      "call_gex": 1,
      "put_gex": -155,
      "total_gex": -154,
      "volume": 2605,
      "probability": 0
    },
    {
      "strike": 686,
      "call_symbol": "",
      "put_symbol": "QQQ260714P00686000",
      "call_oi": 0,
      "put_oi": 724,
      "call_volume": 0,
      "put_volume": 2627,
      "call_iv": 0,
      "put_iv": 0.3711000390625,
      "call_bid": 0,
      "put_bid": 0.01,
      "call_ask": 0,
      "put_ask": 0.02,
      "call_last": 0,
      "put_last": 0.02,
      "call_gex": 0,
      "put_gex": -145711,
      "total_gex": -145711,
      "volume": 2627,
      "probability": 3.91
    },
    {
      "strike": 687,
      "call_symbol": "",
      "put_symbol": "QQQ260714P00687000",
      "call_oi": 0,
      "put_oi": 5443,
      "call_volume": 0,
      "put_volume": 3089,
      "call_iv": 0,
      "put_iv": 0.3632876171875,
      "call_bid": 0,
      "put_bid": 0.01,
      "call_ask": 0,
      "put_ask": 0.02,
      "call_last": 0,
      "put_last": 0.02,
      "call_gex": 0,
      "put_gex": -1171625,
      "total_gex": -1171625,
      "volume": 3089,
      "probability": 4.09
    },
    {
      "strike": 688,
      "call_symbol": "",
      "put_symbol": "QQQ260714P00688000",
      "call_oi": 0,
      "put_oi": 1435,
      "call_volume": 0,
      "put_volume": 3230,
      "call_iv": 0,
      "put_iv": 0.3711000390625,
      "call_bid": 0,
      "put_bid": 0.02,
      "call_ask": 0,
      "put_ask": 0.03,
      "call_last": 0,
      "put_last": 0.02,
      "call_gex": 0,
      "put_gex": -411107,
      "total_gex": -411107,
      "volume": 3230,
      "probability": 5.56
    },
    {
      "strike": 689,
      "call_symbol": "QQQ260714C00689000",
      "put_symbol": "QQQ260714P00689000",
      "call_oi": 1,
      "put_oi": 935,
      "call_volume": 17,
      "put_volume": 2726,
      "call_iv": 0.000010000000000000003,
      "put_iv": 0.3437565625,
      "call_bid": 29.29,
      "put_bid": 0.01,
      "call_ask": 30.71,
      "put_ask": 0.02,
      "call_last": 29.05,
      "put_last": 0.02,
      "call_gex": 0,
      "put_gex": -32,
      "total_gex": -32,
      "volume": 2743,
      "probability": 0
    },
    {
      "strike": 690,
      "call_symbol": "QQQ260714C00690000",
      "put_symbol": "QQQ260714P00690000",
      "call_oi": 46,
      "put_oi": 6969,
      "call_volume": 15,
      "put_volume": 5447,
      "call_iv": 0.000010000000000000003,
      "put_iv": 0.33399103515625,
      "call_bid": 26.66,
      "put_bid": 0.01,
      "call_ask": 29.72,
      "put_ask": 0.02,
      "call_last": 27.78,
      "put_last": 0.02,
      "call_gex": 2,
      "put_gex": -263,
      "total_gex": -261,
      "volume": 5462,
      "probability": 0
    },
    {
      "strike": 691,
      "call_symbol": "QQQ260714C00691000",
      "put_symbol": "QQQ260714P00691000",
      "call_oi": 29,
      "put_oi": 940,
      "call_volume": 13,
      "put_volume": 3709,
      "call_iv": 0.000010000000000000003,
      "put_iv": 0.3242255078124999,
      "call_bid": 27.28,
      "put_bid": 0.01,
      "call_ask": 27.94,
      "put_ask": 0.02,
      "call_last": 27.84,
      "put_last": 0.02,
      "call_gex": 1,
      "put_gex": -39,
      "total_gex": -38,
      "volume": 3722,
      "probability": 0
    },
    {
      "strike": 692,
      "call_symbol": "QQQ260714C00692000",
      "put_symbol": "QQQ260714P00692000",
      "call_oi": 14,
      "put_oi": 1080,
      "call_volume": 10,
      "put_volume": 3916,
      "call_iv": 0.000010000000000000003,
      "put_iv": 0.33008482421874996,
      "call_bid": 25.25,
      "put_bid": 0.02,
      "call_ask": 26.68,
      "put_ask": 0.03,
      "call_last": 26.91,
      "put_last": 0.02,
      "call_gex": 2,
      "put_gex": -148,
      "total_gex": -146,
      "volume": 3926,
      "probability": 0
    },
    {
      "strike": 693,
      "call_symbol": "QQQ260714C00693000",
      "put_symbol": "QQQ260714P00693000",
      "call_oi": 24,
      "put_oi": 5714,
      "call_volume": 15,
      "put_volume": 2581,
      "call_iv": 0.000010000000000000003,
      "put_iv": 0.32031929687499994,
      "call_bid": 23.43,
      "put_bid": 0.02,
      "call_ask": 26.72,
      "put_ask": 0.03,
      "call_last": 26,
      "put_last": 0.03,
      "call_gex": 4,
      "put_gex": -889,
      "total_gex": -885,
      "volume": 2596,
      "probability": 0
    },
    {
      "strike": 694,
      "call_symbol": "QQQ260714C00694000",
      "put_symbol": "QQQ260714P00694000",
      "call_oi": 13,
      "put_oi": 1730,
      "call_volume": 56,
      "put_volume": 2070,
      "call_iv": 0.000010000000000000003,
      "put_iv": 0.3086006640625,
      "call_bid": 24.21,
      "put_bid": 0.02,
      "call_ask": 24.54,
      "put_ask": 0.03,
      "call_last": 23,
      "put_last": 0.02,
      "call_gex": 2,
      "put_gex": -268,
      "total_gex": -266,
      "volume": 2126,
      "probability": 0
    },
    {
      "strike": 695,
      "call_symbol": "QQQ260714C00695000",
      "put_symbol": "QQQ260714P00695000",
      "call_oi": 80,
      "put_oi": 12810,
      "call_volume": 17,
      "put_volume": 7098,
      "call_iv": 0.000010000000000000003,
      "put_iv": 0.3007882421875,
      "call_bid": 23.25,
      "put_bid": 0.03,
      "call_ask": 23.6,
      "put_ask": 0.03,
      "call_last": 24.17,
      "put_last": 0.04,
      "call_gex": 16,
      "put_gex": -2614,
      "total_gex": -2598,
      "volume": 7115,
      "probability": 0
    },
    {
      "strike": 696,
      "call_symbol": "QQQ260714C00696000",
      "put_symbol": "QQQ260714P00696000",
      "call_oi": 14,
      "put_oi": 3106,
      "call_volume": 31,
      "put_volume": 3012,
      "call_iv": 0.000010000000000000003,
      "put_iv": 0.3086006640625,
      "call_bid": 22.16,
      "put_bid": 0.04,
      "call_ask": 22.53,
      "put_ask": 0.05,
      "call_last": 23.12,
      "put_last": 0.05,
      "call_gex": 10,
      "put_gex": -2319,
      "total_gex": -2309,
      "volume": 3043,
      "probability": 0.01
    },
    {
      "strike": 697,
      "call_symbol": "QQQ260714C00697000",
      "put_symbol": "QQQ260714P00697000",
      "call_oi": 7,
      "put_oi": 3516,
      "call_volume": 27,
      "put_volume": 4170,
      "call_iv": 0.000010000000000000003,
      "put_iv": 0.2890696093749999,
      "call_bid": 21.19,
      "put_bid": 0.03,
      "call_ask": 21.51,
      "put_ask": 0.04,
      "call_last": 20.67,
      "put_last": 0.03,
      "call_gex": 3,
      "put_gex": -1679,
      "total_gex": -1676,
      "volume": 4197,
      "probability": 0
    },
    {
      "strike": 698,
      "call_symbol": "QQQ260714C00698000",
      "put_symbol": "QQQ260714P00698000",
      "call_oi": 36,
      "put_oi": 3474,
      "call_volume": 17,
      "put_volume": 3697,
      "call_iv": 0.000010000000000000003,
      "put_iv": 0.28711650390624993,
      "call_bid": 20.24,
      "put_bid": 0.04,
      "call_ask": 20.52,
      "put_ask": 0.05,
      "call_last": 21.85,
      "put_last": 0.04,
      "call_gex": 34,
      "put_gex": -3308,
      "total_gex": -3274,
      "volume": 3714,
      "probability": 0.01
    },
    {
      "strike": 699,
      "call_symbol": "QQQ260714C00699000",
      "put_symbol": "QQQ260714P00699000",
      "call_oi": 99,
      "put_oi": 6606,
      "call_volume": 16,
      "put_volume": 4556,
      "call_iv": 0.000010000000000000003,
      "put_iv": 0.27735097656249996,
      "call_bid": 19.18,
      "put_bid": 0.04,
      "call_ask": 19.52,
      "put_ask": 0.05,
      "call_last": 20.17,
      "put_last": 0.05,
      "call_gex": 115,
      "put_gex": -7650,
      "total_gex": -7535,
      "volume": 4572,
      "probability": 0.01
    },
    {
      "strike": 700,
      "call_symbol": "QQQ260714C00700000",
      "put_symbol": "QQQ260714P00700000",
      "call_oi": 169,
      "put_oi": 6329,
      "call_volume": 71,
      "put_volume": 13000,
      "call_iv": 0.000010000000000000003,
      "put_iv": 0.273444765625,
      "call_bid": 18.25,
      "put_bid": 0.05,
      "call_ask": 18.53,
      "put_ask": 0.06,
      "call_last": 17.52,
      "put_last": 0.05,
      "call_gex": 348,
      "put_gex": -13041,
      "total_gex": -12693,
      "volume": 13071,
      "probability": 0.01
    },
    {
      "strike": 701,
      "call_symbol": "QQQ260714C00701000",
      "put_symbol": "QQQ260714P00701000",
      "call_oi": 54,
      "put_oi": 1699,
      "call_volume": 11,
      "put_volume": 6017,
      "call_iv": 0.000010000000000000003,
      "put_iv": 0.26270268554687504,
      "call_bid": 17.33,
      "put_bid": 0.05,
      "call_ask": 17.68,
      "put_ask": 0.06,
      "call_last": 18.61,
      "put_last": 0.06,
      "call_gex": 131,
      "put_gex": -4128,
      "total_gex": -3997,
      "volume": 6028,
      "probability": 0.02
    },
    {
      "strike": 702,
      "call_symbol": "QQQ260714C00702000",
      "put_symbol": "QQQ260714P00702000",
      "call_oi": 57,
      "put_oi": 1029,
      "call_volume": 53,
      "put_volume": 4508,
      "call_iv": 0.000010000000000000003,
      "put_iv": 0.256843369140625,
      "call_bid": 16.3,
      "put_bid": 0.06,
      "call_ask": 16.62,
      "put_ask": 0.07,
      "call_last": 16.53,
      "put_last": 0.08,
      "call_gex": 224,
      "put_gex": -4037,
      "total_gex": -3813,
      "volume": 4561,
      "probability": 0.03
    },
    {
      "strike": 703,
      "call_symbol": "QQQ260714C00703000",
      "put_symbol": "QQQ260714P00703000",
      "call_oi": 194,
      "put_oi": 1637,
      "call_volume": 101,
      "put_volume": 7818,
      "call_iv": 0.000010000000000000003,
      "put_iv": 0.25586681640625003,
      "call_bid": 15.29,
      "put_bid": 0.08,
      "call_ask": 15.63,
      "put_ask": 0.09,
      "call_last": 13.8,
      "put_last": 0.07,
      "call_gex": 1632,
      "put_gex": -13769,
      "total_gex": -12137,
      "volume": 7919,
      "probability": 0.06
    },
    {
      "strike": 704,
      "call_symbol": "QQQ260714C00704000",
      "put_symbol": "QQQ260714P00704000",
      "call_oi": 214,
      "put_oi": 3550,
      "call_volume": 122,
      "put_volume": 12462,
      "call_iv": 0.000010000000000000003,
      "put_iv": 0.24414818359375,
      "call_bid": 14.25,
      "put_bid": 0.08,
      "call_ask": 14.56,
      "put_ask": 0.09,
      "call_last": 14.1,
      "put_last": 0.1,
      "call_gex": 2127,
      "put_gex": -35287,
      "total_gex": -33160,
      "volume": 12584,
      "probability": 0.06
    },
    {
      "strike": 705,
      "call_symbol": "QQQ260714C00705000",
      "put_symbol": "QQQ260714P00705000",
      "call_oi": 285,
      "put_oi": 8797,
      "call_volume": 183,
      "put_volume": 19242,
      "call_iv": 0.000010000000000000003,
      "put_iv": 0.24024197265624997,
      "call_bid": 13.33,
      "put_bid": 0.1,
      "call_ask": 13.65,
      "put_ask": 0.11,
      "call_last": 13.5,
      "put_last": 0.09,
      "call_gex": 5213,
      "put_gex": -160909,
      "total_gex": -155696,
      "volume": 19425,
      "probability": 0.12
    },
    {
      "strike": 706,
      "call_symbol": "QQQ260714C00706000",
      "put_symbol": "QQQ260714P00706000",
      "call_oi": 423,
      "put_oi": 1802,
      "call_volume": 414,
      "put_volume": 11879,
      "call_iv": 0.000010000000000000003,
      "put_iv": 0.23535920898437498,
      "call_bid": 12.4,
      "put_bid": 0.12,
      "call_ask": 12.75,
      "put_ask": 0.13,
      "call_last": 12.5,
      "put_last": 0.13,
      "call_gex": 13495,
      "put_gex": -57489,
      "total_gex": -43994,
      "volume": 12293,
      "probability": 0.2
    },
    {
      "strike": 707,
      "call_symbol": "QQQ260714C00707000",
      "put_symbol": "QQQ260714P00707000",
      "call_oi": 429,
      "put_oi": 1383,
      "call_volume": 119,
      "put_volume": 14418,
      "call_iv": 0.000010000000000000003,
      "put_iv": 0.23194127441406248,
      "call_bid": 11.3,
      "put_bid": 0.15,
      "call_ask": 11.62,
      "put_ask": 0.16,
      "call_last": 11.52,
      "put_last": 0.15,
      "call_gex": 25475,
      "put_gex": -82126,
      "total_gex": -56651,
      "volume": 14537,
      "probability": 0.36
    },
    {
      "strike": 708,
      "call_symbol": "QQQ260714C00708000",
      "put_symbol": "QQQ260714P00708000",
      "call_oi": 273,
      "put_oi": 3169,
      "call_volume": 186,
      "put_volume": 15417,
      "call_iv": 0.000010000000000000003,
      "put_iv": 0.22657023437499998,
      "call_bid": 10.46,
      "put_bid": 0.18,
      "call_ask": 10.81,
      "put_ask": 0.19,
      "call_last": 11.7,
      "put_last": 0.19,
      "call_gex": 27504,
      "put_gex": -319270,
      "total_gex": -291766,
      "volume": 15603,
      "probability": 0.6
    },
    {
      "strike": 709,
      "call_symbol": "QQQ260714C00709000",
      "put_symbol": "QQQ260714P00709000",
      "call_oi": 714,
      "put_oi": 1014,
      "call_volume": 795,
      "put_volume": 18224,
      "call_iv": 0.000010000000000000003,
      "put_iv": 0.2243729907226562,
      "call_bid": 9.31,
      "put_bid": 0.22,
      "call_ask": 9.6,
      "put_ask": 0.24,
      "call_last": 8.69,
      "put_last": 0.23,
      "call_gex": 136915,
      "put_gex": -194443,
      "total_gex": -57528,
      "volume": 19019,
      "probability": 1.13
    },
    {
      "strike": 710,
      "call_symbol": "QQQ260714C00710000",
      "put_symbol": "QQQ260714P00710000",
      "call_oi": 1529,
      "put_oi": 5000,
      "call_volume": 1276,
      "put_volume": 52035,
      "call_iv": 0.000010000000000000003,
      "put_iv": 0.21826953613281247,
      "call_bid": 8.44,
      "put_bid": 0.27,
      "call_ask": 8.75,
      "put_ask": 0.28,
      "call_last": 8.11,
      "put_last": 0.28,
      "call_gex": 478899,
      "put_gex": -1566053,
      "total_gex": -1087154,
      "volume": 53311,
      "probability": 1.79
    },
    {
      "strike": 711,
      "call_symbol": "QQQ260714C00711000",
      "put_symbol": "QQQ260714P00711000",
      "call_oi": 1066,
      "put_oi": 1534,
      "call_volume": 1991,
      "put_volume": 24122,
      "call_iv": 0.000010000000000000003,
      "put_iv": 0.21558401611328126,
      "call_bid": 7.69,
      "put_bid": 0.34,
      "call_ask": 7.79,
      "put_ask": 0.35,
      "call_last": 7.56,
      "put_last": 0.34,
      "call_gex": 600315,
      "put_gex": -863868,
      "total_gex": -263553,
      "volume": 26113,
      "probability": 3.18
    },
    {
      "strike": 712,
      "call_symbol": "QQQ260714C00712000",
      "put_symbol": "QQQ260714P00712000",
      "call_oi": 3105,
      "put_oi": 2509,
      "call_volume": 3595,
      "put_volume": 38042,
      "call_iv": 0.000010000000000000003,
      "put_iv": 0.21216608154296873,
      "call_bid": 6.72,
      "put_bid": 0.42,
      "call_ask": 6.81,
      "put_ask": 0.43,
      "call_last": 6.66,
      "put_last": 0.42,
      "call_gex": 2996867,
      "put_gex": -2421623,
      "total_gex": 575244,
      "volume": 41637,
      "probability": 5.36
    },
    {
      "strike": 713,
      "call_symbol": "QQQ260714C00713000",
      "put_symbol": "QQQ260714P00713000",
      "call_oi": 3165,
      "put_oi": 1406,
      "call_volume": 5394,
      "put_volume": 29767,
      "call_iv": 0.000010000000000000003,
      "put_iv": 0.21021297607421874,
      "call_bid": 5.88,
      "put_bid": 0.53,
      "call_ask": 5.96,
      "put_ask": 0.54,
      "call_last": 5.87,
      "put_last": 0.55,
      "call_gex": 5230744,
      "put_gex": -2323673,
      "total_gex": 2907071,
      "volume": 35161,
      "probability": 9.09
    },
    {
      "strike": 714,
      "call_symbol": "QQQ260714C00714000",
      "put_symbol": "QQQ260714P00714000",
      "call_oi": 3106,
      "put_oi": 1860,
      "call_volume": 6149,
      "put_volume": 44216,
      "call_iv": 0.000010000000000000003,
      "put_iv": 0.21021297607421874,
      "call_bid": 5.08,
      "put_bid": 0.68,
      "call_ask": 5.15,
      "put_ask": 0.69,
      "call_last": 5.03,
      "put_last": 0.69,
      "call_gex": 8632494,
      "put_gex": -5169491,
      "total_gex": 3463003,
      "volume": 50365,
      "probability": 15.29
    },
    {
      "strike": 715,
      "call_symbol": "QQQ260714C00715000",
      "put_symbol": "QQQ260714P00715000",
      "call_oi": 5524,
      "put_oi": 3274,
      "call_volume": 23813,
      "put_volume": 91284,
      "call_iv": 0.000010000000000000003,
      "put_iv": 0.21363091064453127,
      "call_bid": 4.22,
      "put_bid": 0.89,
      "call_ask": 4.29,
      "put_ask": 0.91,
      "call_last": 4.31,
      "put_last": 0.88,
      "call_gex": 24944710,
      "put_gex": -14784392,
      "total_gex": 10160318,
      "volume": 115097,
      "probability": 25.25
    },
    {
      "strike": 716,
      "call_symbol": "QQQ260714C00716000",
      "put_symbol": "QQQ260714P00716000",
      "call_oi": 1989,
      "put_oi": 9392,
      "call_volume": 35315,
      "put_volume": 77768,
      "call_iv": 0.000010000000000000003,
      "put_iv": 0.20996883789062498,
      "call_bid": 3.46,
      "put_bid": 1.08,
      "call_ask": 3.48,
      "put_ask": 1.09,
      "call_last": 3.48,
      "put_last": 1.09,
      "call_gex": 12908776,
      "put_gex": -60954866,
      "total_gex": -48046090,
      "volume": 113083,
      "probability": 35.67
    },
    {
      "strike": 717,
      "call_symbol": "QQQ260714C00717000",
      "put_symbol": "QQQ260714P00717000",
      "call_oi": 2014,
      "put_oi": 1355,
      "call_volume": 54668,
      "put_volume": 75523,
      "call_iv": 0.000010000000000000003,
      "put_iv": 0.2172929833984375,
      "call_bid": 2.81,
      "put_bid": 1.42,
      "call_ask": 2.81,
      "put_ask": 1.44,
      "call_last": 2.81,
      "put_last": 1.43,
      "call_gex": 18408800,
      "put_gex": -12385265,
      "total_gex": 6023535,
      "volume": 130191,
      "probability": 51.98
    },
    {
      "strike": 718,
      "call_symbol": "QQQ260714C00718000",
      "put_symbol": "QQQ260714P00718000",
      "call_oi": 3337,
      "put_oi": 1220,
      "call_volume": 89399,
      "put_volume": 64373,
      "call_iv": 0.000010000000000000003,
      "put_iv": 0.2264481652832031,
      "call_bid": 2.21,
      "put_bid": 1.85,
      "call_ask": 2.24,
      "put_ask": 1.87,
      "call_last": 2.21,
      "put_last": 1.85,
      "call_gex": 38769775,
      "put_gex": -14174146,
      "total_gex": 24595629,
      "volume": 153772,
      "probability": 68.86
    },
    {
      "strike": 719,
      "call_symbol": "QQQ260714C00719000",
      "put_symbol": "QQQ260714P00719000",
      "call_oi": 4918,
      "put_oi": 376,
      "call_volume": 114564,
      "put_volume": 48611,
      "call_iv": 0.000010000000000000003,
      "put_iv": 0.22461712890624996,
      "call_bid": 1.6,
      "put_bid": 2.18,
      "call_ask": 1.61,
      "put_ask": 2.2,
      "call_last": 1.6,
      "put_last": 2.17,
      "call_gex": 68373031,
      "put_gex": -5227381,
      "total_gex": 63145650,
      "volume": 163175,
      "probability": 81.73
    },
    {
      "strike": 720,
      "call_symbol": "QQQ260714C00720000",
      "put_symbol": "QQQ260714P00720000",
      "call_oi": 11991,
      "put_oi": 1845,
      "call_volume": 172579,
      "put_volume": 26414,
      "call_iv": 0.000010000000000000003,
      "put_iv": 0.2401199035644531,
      "call_bid": 1.16,
      "put_bid": 2.8,
      "call_ask": 1.17,
      "put_ask": 2.83,
      "call_last": 1.16,
      "put_last": 2.8,
      "call_gex": 177933360,
      "put_gex": -27377787,
      "total_gex": 150555573,
      "volume": 198993,
      "probability": 93.25
    },
    {
      "strike": 721,
      "call_symbol": "QQQ260714C00721000",
      "put_symbol": "QQQ260714P00721000",
      "call_oi": 3285,
      "put_oi": 714,
      "call_volume": 79740,
      "put_volume": 7595,
      "call_iv": 0.0273534765625,
      "put_iv": 0.24683370361328127,
      "call_bid": 0.83,
      "put_bid": 3.35,
      "call_ask": 0.85,
      "put_ask": 3.38,
      "call_last": 0.84,
      "put_last": 3.42,
      "call_gex": 45368432,
      "put_gex": -9860901,
      "total_gex": 35507531,
      "volume": 87335,
      "probability": 99.1
    },
    {
      "strike": 722,
      "call_symbol": "QQQ260714C00722000",
      "put_symbol": "QQQ260714P00722000",
      "call_oi": 3034,
      "put_oi": 1133,
      "call_volume": 103804,
      "put_volume": 6476,
      "call_iv": 0.04651832397460938,
      "put_iv": 0.2690502783203125,
      "call_bid": 0.55,
      "put_bid": 4.14,
      "call_ask": 0.56,
      "put_ask": 4.21,
      "call_last": 0.56,
      "put_last": 4.29,
      "call_gex": 36688471,
      "put_gex": -13700737,
      "total_gex": 22987734,
      "volume": 110280,
      "probability": 99.87
    },
    {
      "strike": 723,
      "call_symbol": "QQQ260714C00723000",
      "put_symbol": "QQQ260714P00723000",
      "call_oi": 1843,
      "put_oi": 642,
      "call_volume": 66584,
      "put_volume": 1417,
      "call_iv": 0.05933557861328125,
      "put_iv": 0.28882547119140617,
      "call_bid": 0.37,
      "put_bid": 4.94,
      "call_ask": 0.39,
      "put_ask": 5.04,
      "call_last": 0.39,
      "put_last": 5.09,
      "call_gex": 19832147,
      "put_gex": -6908431,
      "total_gex": 12923716,
      "volume": 68001,
      "probability": 98.05
    },
    {
      "strike": 724,
      "call_symbol": "QQQ260714C00724000",
      "put_symbol": "QQQ260714P00724000",
      "call_oi": 5819,
      "put_oi": 774,
      "call_volume": 45347,
      "put_volume": 1244,
      "call_iv": 0.0669038623046875,
      "put_iv": 0.3092110095214844,
      "call_bid": 0.23,
      "put_bid": 5.82,
      "call_ask": 0.25,
      "put_ask": 5.91,
      "call_last": 0.24,
      "put_last": 6.01,
      "call_gex": 56084518,
      "put_gex": -7459945,
      "total_gex": 48624573,
      "volume": 46591,
      "probability": 94.87
    },
    {
      "strike": 725,
      "call_symbol": "QQQ260714C00725000",
      "put_symbol": "QQQ260714P00725000",
      "call_oi": 6436,
      "put_oi": 919,
      "call_volume": 45571,
      "put_volume": 1372,
      "call_iv": 0.07349559326171876,
      "put_iv": 0.3327703442382813,
      "call_bid": 0.15,
      "put_bid": 6.52,
      "call_ask": 0.16,
      "put_ask": 6.85,
      "call_last": 0.15,
      "put_last": 8.28,
      "call_gex": 55169500,
      "put_gex": -7877683,
      "total_gex": 47291817,
      "volume": 46943,
      "probability": 91.14
    },
    {
      "strike": 726,
      "call_symbol": "QQQ260714C00726000",
      "put_symbol": "QQQ260714P00726000",
      "call_oi": 2180,
      "put_oi": 672,
      "call_volume": 74437,
      "put_volume": 520,
      "call_iv": 0.07886663330078125,
      "put_iv": 0.3619448571777344,
      "call_bid": 0.09,
      "put_bid": 7.58,
      "call_ask": 0.1,
      "put_ask": 7.89,
      "call_last": 0.1,
      "put_last": 7.54,
      "call_gex": 16531982,
      "put_gex": -5096097,
      "total_gex": 11435885,
      "volume": 74957,
      "probability": 87.49
    },
    {
      "strike": 727,
      "call_symbol": "QQQ260714C00727000",
      "put_symbol": "QQQ260714P00727000",
      "call_oi": 2958,
      "put_oi": 263,
      "call_volume": 11935,
      "put_volume": 581,
      "call_iv": 0.08594664062500001,
      "put_iv": 0.3895324719238281,
      "call_bid": 0.06,
      "put_bid": 8.59,
      "call_ask": 0.07,
      "put_ask": 8.92,
      "call_last": 0.06,
      "put_last": 9.31,
      "call_gex": 19965093,
      "put_gex": -1775125,
      "total_gex": 18189968,
      "volume": 12516,
      "probability": 83.99
    },
    {
      "strike": 728,
      "call_symbol": "QQQ260714C00728000",
      "put_symbol": "QQQ260714P00728000",
      "call_oi": 2162,
      "put_oi": 34,
      "call_volume": 13574,
      "put_volume": 123,
      "call_iv": 0.0922942333984375,
      "put_iv": 0.4063780065917969,
      "call_bid": 0.04,
      "put_bid": 9.49,
      "call_ask": 0.05,
      "put_ask": 9.81,
      "call_last": 0.05,
      "put_last": 10.88,
      "call_gex": 13240700,
      "put_gex": -208226,
      "total_gex": 13032474,
      "volume": 13697,
      "probability": 79.93
    },
    {
      "strike": 729,
      "call_symbol": "QQQ260714C00729000",
      "put_symbol": "QQQ260714P00729000",
      "call_oi": 1958,
      "put_oi": 0,
      "call_volume": 16197,
      "put_volume": 34,
      "call_iv": 0.09571216796875001,
      "put_iv": 0.42664147583007817,
      "call_bid": 0.02,
      "put_bid": 10.46,
      "call_ask": 0.03,
      "put_ask": 10.76,
      "call_last": 0.03,
      "put_last": 10.79,
      "call_gex": 10888788,
      "put_gex": 0,
      "total_gex": 10888788,
      "volume": 16231,
      "probability": 76.02
    },
    {
      "strike": 730,
      "call_symbol": "QQQ260714C00730000",
      "put_symbol": "QQQ260714P00730000",
      "call_oi": 6619,
      "put_oi": 55,
      "call_volume": 25648,
      "put_volume": 185,
      "call_iv": 0.100594931640625,
      "put_iv": 0.45288633056640626,
      "call_bid": 0.01,
      "put_bid": 11.46,
      "call_ask": 0.02,
      "put_ask": 11.8,
      "call_last": 0.02,
      "put_last": 12.27,
      "call_gex": 33328650,
      "put_gex": -276941,
      "total_gex": 33051709,
      "volume": 25833,
      "probability": 72.94
    },
    {
      "strike": 731,
      "call_symbol": "QQQ260714C00731000",
      "put_symbol": "QQQ260714P00731000",
      "call_oi": 3019,
      "put_oi": 0,
      "call_volume": 9879,
      "put_volume": 35,
      "call_iv": 0.11133701171874999,
      "put_iv": 0.4815725671386719,
      "call_bid": 0.01,
      "put_bid": 12.54,
      "call_ask": 0.02,
      "put_ask": 12.88,
      "call_last": 0.02,
      "put_last": 11.7,
      "call_gex": 13776295,
      "put_gex": 0,
      "total_gex": 13776295,
      "volume": 9914,
      "probability": 70.81
    },
    {
      "strike": 732,
      "call_symbol": "QQQ260714C00732000",
      "put_symbol": "QQQ260714P00732000",
      "call_oi": 3947,
      "put_oi": 0,
      "call_volume": 4024,
      "put_volume": 27,
      "call_iv": 0.11133701171874999,
      "put_iv": 0.4963429272460938,
      "call_bid": 0,
      "put_bid": 13.48,
      "call_ask": 0.01,
      "put_ask": 13.78,
      "call_last": 0.01,
      "put_last": 12.77,
      "call_gex": 16585370,
      "put_gex": 0,
      "total_gex": 16585370,
      "volume": 4051,
      "probability": 66.83
    },
    {
      "strike": 733,
      "call_symbol": "QQQ260714C00733000",
      "put_symbol": "QQQ260714P00733000",
      "call_oi": 1018,
      "put_oi": 0,
      "call_volume": 8897,
      "put_volume": 24,
      "call_iv": 0.1211025390625,
      "put_iv": 0.5002491381835938,
      "call_bid": 0,
      "put_bid": 14.37,
      "call_ask": 0.01,
      "put_ask": 14.73,
      "call_last": 0.02,
      "put_last": 15.58,
      "call_gex": 3936325,
      "put_gex": 0,
      "total_gex": 3936325,
      "volume": 8921,
      "probability": 62.88
    },
    {
      "strike": 734,
      "call_symbol": "QQQ260714C00734000",
      "put_symbol": "QQQ260714P00734000",
      "call_oi": 847,
      "put_oi": 1,
      "call_volume": 2280,
      "put_volume": 7,
      "call_iv": 0.1289149609375,
      "put_iv": 0.521367091064453,
      "call_bid": 0,
      "put_bid": 15.37,
      "call_ask": 0.01,
      "put_ask": 15.73,
      "call_last": 0.01,
      "put_last": 14.74,
      "call_gex": 3013053,
      "put_gex": -3557,
      "total_gex": 3009496,
      "volume": 2287,
      "probability": 60.54
    },
    {
      "strike": 735,
      "call_symbol": "QQQ260714C00735000",
      "put_symbol": "QQQ260714P00735000",
      "call_oi": 3015,
      "put_oi": 32,
      "call_volume": 3463,
      "put_volume": 5,
      "call_iv": 0.13868048828125001,
      "put_iv": 0.5583540258789064,
      "call_bid": 0,
      "put_bid": 16.53,
      "call_ask": 0.01,
      "put_ask": 16.97,
      "call_last": 0.01,
      "put_last": 15.78,
      "call_gex": 9918139,
      "put_gex": -105267,
      "total_gex": 9812872,
      "volume": 3468,
      "probability": 60.01
    },
    {
      "strike": 736,
      "call_symbol": "QQQ260714C00736000",
      "put_symbol": "QQQ260714P00736000",
      "call_oi": 757,
      "put_oi": 0,
      "call_volume": 1243,
      "put_volume": 17,
      "call_iv": 0.148446015625,
      "put_iv": 0.5716595568847658,
      "call_bid": 0,
      "put_bid": 17.43,
      "call_ask": 0.01,
      "put_ask": 17.89,
      "call_last": 0.01,
      "put_last": 16.78,
      "call_gex": 2310311,
      "put_gex": 0,
      "total_gex": 2310311,
      "volume": 1260,
      "probability": 57.52
    },
    {
      "strike": 737,
      "call_symbol": "QQQ260714C00737000",
      "put_symbol": "QQQ260714P00737000",
      "call_oi": 4598,
      "put_oi": 0,
      "call_volume": 710,
      "put_volume": 30,
      "call_iv": 0.1562584375,
      "put_iv": 0.5886271606445312,
      "call_bid": 0,
      "put_bid": 18.41,
      "call_ask": 0.01,
      "put_ask": 18.83,
      "call_last": 0.01,
      "put_last": 18.75,
      "call_gex": 13052176,
      "put_gex": 0,
      "total_gex": 13052176,
      "volume": 740,
      "probability": 55.34
    },
    {
      "strike": 738,
      "call_symbol": "QQQ260714C00738000",
      "put_symbol": "QQQ260714P00738000",
      "call_oi": 946,
      "put_oi": 0,
      "call_volume": 154,
      "put_volume": 104,
      "call_iv": 0.16407085937500002,
      "put_iv": 0.6086464916992189,
      "call_bid": 0,
      "put_bid": 19.41,
      "call_ask": 0.01,
      "put_ask": 19.83,
      "call_last": 0.01,
      "put_last": 21.36,
      "call_gex": 2506269,
      "put_gex": 0,
      "total_gex": 2506269,
      "volume": 258,
      "probability": 53.58
    },
    {
      "strike": 739,
      "call_symbol": "QQQ260714C00739000",
      "put_symbol": "QQQ260714P00739000",
      "call_oi": 1165,
      "put_oi": 0,
      "call_volume": 166,
      "put_volume": 12,
      "call_iv": 0.1757894921875,
      "put_iv": 0.6284216845703126,
      "call_bid": 0,
      "put_bid": 20.41,
      "call_ask": 0.01,
      "put_ask": 20.83,
      "call_last": 0.01,
      "put_last": 22.3,
      "call_gex": 2892625,
      "put_gex": 0,
      "total_gex": 2892625,
      "volume": 178,
      "probability": 52.26
    },
    {
      "strike": 740,
      "call_symbol": "QQQ260714C00740000",
      "put_symbol": "QQQ260714P00740000",
      "call_oi": 1376,
      "put_oi": 14,
      "call_volume": 202,
      "put_volume": 30,
      "call_iv": 0.18360191406249998,
      "put_iv": 0.650516190185547,
      "call_bid": 0,
      "put_bid": 21.43,
      "call_ask": 0.01,
      "put_ask": 21.87,
      "call_last": 0.03,
      "put_last": 20.9,
      "call_gex": 3209380,
      "put_gex": -32654,
      "total_gex": 3176726,
      "volume": 232,
      "probability": 50.92
    },
    {
      "strike": 741,
      "call_symbol": "QQQ260714C00741000",
      "put_symbol": "QQQ260714P00741000",
      "call_oi": 1143,
      "put_oi": 0,
      "call_volume": 2,
      "put_volume": 0,
      "call_iv": 0.1914143359375,
      "put_iv": 0.6654086193847659,
      "call_bid": 0,
      "put_bid": 22.4,
      "call_ask": 0.01,
      "put_ask": 22.8,
      "call_last": 0.01,
      "put_last": 32.14,
      "call_gex": 2502260,
      "put_gex": 0,
      "total_gex": 2502260,
      "volume": 2,
      "probability": 49.09
    },
    {
      "strike": 742,
      "call_symbol": "QQQ260714C00742000",
      "put_symbol": "QQQ260714P00742000",
      "call_oi": 1412,
      "put_oi": 0,
      "call_volume": 5,
      "put_volume": 9,
      "call_iv": 0.1992267578125,
      "put_iv": 0.6906769213867189,
      "call_bid": 0,
      "put_bid": 23.45,
      "call_ask": 0.01,
      "put_ask": 23.89,
      "call_last": 0.01,
      "put_last": 26.07,
      "call_gex": 2922604,
      "put_gex": 0,
      "total_gex": 2922604,
      "volume": 14,
      "probability": 48.21
    },
    {
      "strike": 743,
      "call_symbol": "QQQ260714C00743000",
      "put_symbol": "QQQ260714P00743000",
      "call_oi": 657,
      "put_oi": 0,
      "call_volume": 5,
      "put_volume": 8,
      "call_iv": 0.21094539062499998,
      "put_iv": 0.733279034423828,
      "call_bid": 0,
      "put_bid": 23.27,
      "call_ask": 0.01,
      "put_ask": 26.61,
      "call_last": 0.01,
      "put_last": 23.6,
      "call_gex": 1302486,
      "put_gex": 0,
      "total_gex": 1302486,
      "volume": 13,
      "probability": 48.99
    },
    {
      "strike": 744,
      "call_symbol": "QQQ260714C00744000",
      "put_symbol": "QQQ260714P00744000",
      "call_oi": 1118,
      "put_oi": 1,
      "call_volume": 4,
      "put_volume": 8,
      "call_iv": 0.21875781249999998,
      "put_iv": 0.7521997436523438,
      "call_bid": 0,
      "put_bid": 24.27,
      "call_ask": 0.01,
      "put_ask": 27.61,
      "call_last": 0.01,
      "put_last": 24.59,
      "call_gex": 2099893,
      "put_gex": -1878,
      "total_gex": 2098015,
      "volume": 12,
      "probability": 47.73
    },
    {
      "strike": 745,
      "call_symbol": "QQQ260714C00745000",
      "put_symbol": "QQQ260714P00745000",
      "call_oi": 859,
      "put_oi": 20,
      "call_volume": 584,
      "put_volume": 502,
      "call_iv": 0.22657023437499998,
      "put_iv": 0.7611107873535157,
      "call_bid": 0,
      "put_bid": 25.27,
      "call_ask": 0.01,
      "put_ask": 28.39,
      "call_last": 0.01,
      "put_last": 28.03,
      "call_gex": 1522854,
      "put_gex": -35456,
      "total_gex": 1487398,
      "volume": 1086,
      "probability": 45.83
    },
    {
      "strike": 746,
      "call_symbol": "QQQ260714C00746000",
      "put_symbol": "",
      "call_oi": 318,
      "put_oi": 0,
      "call_volume": 60,
      "put_volume": 0,
      "call_iv": 0.23438265625,
      "put_iv": 0,
      "call_bid": 0,
      "put_bid": 0,
      "call_ask": 0.01,
      "put_ask": 0,
      "call_last": 0.01,
      "put_last": 0,
      "call_gex": 59880,
      "put_gex": 0,
      "total_gex": 59880,
      "volume": 60,
      "probability": 2.31
    },
    {
      "strike": 747,
      "call_symbol": "QQQ260714C00747000",
      "put_symbol": "QQQ260714P00747000",
      "call_oi": 437,
      "put_oi": 0,
      "call_volume": 1882,
      "put_volume": 2,
      "call_iv": 0.242195078125,
      "put_iv": 0.8103046313476561,
      "call_bid": 0,
      "put_bid": 27.51,
      "call_ask": 0.01,
      "put_ask": 30.42,
      "call_last": 0.01,
      "put_last": 32.14,
      "call_gex": 705630,
      "put_gex": 0,
      "total_gex": 705630,
      "volume": 1884,
      "probability": 44.48
    },
    {
      "strike": 748,
      "call_symbol": "QQQ260714C00748000",
      "put_symbol": "",
      "call_oi": 424,
      "put_oi": 0,
      "call_volume": 1696,
      "put_volume": 0,
      "call_iv": 0.2500075,
      "put_iv": 0,
      "call_bid": 0,
      "put_bid": 0,
      "call_ask": 0.01,
      "put_ask": 0,
      "call_last": 0.01,
      "put_last": 0,
      "call_gex": 66974,
      "put_gex": 0,
      "total_gex": 66974,
      "volume": 1696,
      "probability": 2.07
    },
    {
      "strike": 749,
      "call_symbol": "QQQ260714C00749000",
      "put_symbol": "",
      "call_oi": 888,
      "put_oi": 0,
      "call_volume": 1,
      "put_volume": 0,
      "call_iv": 0.2617261328125,
      "put_iv": 0,
      "call_bid": 0,
      "put_bid": 0,
      "call_ask": 0.01,
      "put_ask": 0,
      "call_last": 0.01,
      "put_last": 0,
      "call_gex": 143036,
      "put_gex": 0,
      "total_gex": 143036,
      "volume": 1,
      "probability": 2.21
    },
    {
      "strike": 750,
      "call_symbol": "QQQ260714C00750000",
      "put_symbol": "QQQ260714P00750000",
      "call_oi": 1719,
      "put_oi": 4,
      "call_volume": 1,
      "put_volume": 24,
      "call_iv": 0.2695385546875,
      "put_iv": 0.8518081225585938,
      "call_bid": 0,
      "put_bid": 30.27,
      "call_ask": 0.01,
      "put_ask": 33.39,
      "call_last": 0.01,
      "put_last": 38.81,
      "call_gex": 2398159,
      "put_gex": -5580,
      "total_gex": 2392579,
      "volume": 25,
      "probability": 40.94
    },
    {
      "strike": 751,
      "call_symbol": "QQQ260714C00751000",
      "put_symbol": "QQQ260714P00751000",
      "call_oi": 466,
      "put_oi": 0,
      "call_volume": 224,
      "put_volume": 0,
      "call_iv": 0.27735097656249996,
      "put_iv": 0.8696302099609375,
      "call_bid": 0,
      "put_bid": 31.27,
      "call_ask": 0.01,
      "put_ask": 34.39,
      "call_last": 0.01,
      "put_last": 34,
      "call_gex": 621811,
      "put_gex": 0,
      "total_gex": 621811,
      "volume": 224,
      "probability": 40.05
    },
    {
      "strike": 752,
      "call_symbol": "QQQ260714C00752000",
      "put_symbol": "",
      "call_oi": 660,
      "put_oi": 0,
      "call_volume": 551,
      "put_volume": 0,
      "call_iv": 0.28516339843749994,
      "put_iv": 0,
      "call_bid": 0,
      "put_bid": 0,
      "call_ask": 0.01,
      "put_ask": 0,
      "call_last": 0.01,
      "put_last": 0,
      "call_gex": 84523,
      "put_gex": 0,
      "total_gex": 84523,
      "volume": 551,
      "probability": 1.91
    },
    {
      "strike": 753,
      "call_symbol": "QQQ260714C00753000",
      "put_symbol": "",
      "call_oi": 197,
      "put_oi": 0,
      "call_volume": 4,
      "put_volume": 0,
      "call_iv": 0.29688203124999996,
      "put_iv": 0,
      "call_bid": 0,
      "put_bid": 0,
      "call_ask": 0.01,
      "put_ask": 0,
      "call_last": 0.01,
      "put_last": 0,
      "call_gex": 25765,
      "put_gex": 0,
      "total_gex": 25765,
      "volume": 4,
      "probability": 2.03
    },
    {
      "strike": 754,
      "call_symbol": "QQQ260714C00754000",
      "put_symbol": "",
      "call_oi": 221,
      "put_oi": 0,
      "call_volume": 4,
      "put_volume": 0,
      "call_iv": 0.304694453125,
      "put_iv": 0,
      "call_bid": 0,
      "put_bid": 0,
      "call_ask": 0.01,
      "put_ask": 0,
      "call_last": 0.01,
      "put_last": 0,
      "call_gex": 26982,
      "put_gex": 0,
      "total_gex": 26982,
      "volume": 4,
      "probability": 1.95
    },
    {
      "strike": 755,
      "call_symbol": "QQQ260714C00755000",
      "put_symbol": "QQQ260714P00755000",
      "call_oi": 1985,
      "put_oi": 0,
      "call_volume": 8,
      "put_volume": 3,
      "call_iv": 0.31250687499999996,
      "put_iv": 0.9389654541015625,
      "call_bid": 0,
      "put_bid": 35.07,
      "call_ask": 0.01,
      "put_ask": 38.59,
      "call_last": 0.01,
      "put_last": 42.59,
      "call_gex": 2246040,
      "put_gex": 0,
      "total_gex": 2246040,
      "volume": 11,
      "probability": 37.06
    },
    {
      "strike": 756,
      "call_symbol": "QQQ260714C00756000",
      "put_symbol": "",
      "call_oi": 1207,
      "put_oi": 0,
      "call_volume": 5,
      "put_volume": 0,
      "call_iv": 0.32031929687499994,
      "put_iv": 0,
      "call_bid": 0,
      "put_bid": 0,
      "call_ask": 0.01,
      "put_ask": 0,
      "call_last": 0.01,
      "put_last": 0,
      "call_gex": 129389,
      "put_gex": 0,
      "total_gex": 129389,
      "volume": 5,
      "probability": 1.8
    },
    {
      "strike": 757,
      "call_symbol": "QQQ260714C00757000",
      "put_symbol": "",
      "call_oi": 24,
      "put_oi": 0,
      "call_volume": 8,
      "put_volume": 0,
      "call_iv": 0.32813171874999997,
      "put_iv": 0,
      "call_bid": 0,
      "put_bid": 0,
      "call_ask": 0.01,
      "put_ask": 0,
      "call_last": 0.02,
      "put_last": 0,
      "call_gex": 2419,
      "put_gex": 0,
      "total_gex": 2419,
      "volume": 8,
      "probability": 1.73
    },
    {
      "strike": 758,
      "call_symbol": "QQQ260714C00758000",
      "put_symbol": "",
      "call_oi": 150,
      "put_oi": 0,
      "call_volume": 22,
      "put_volume": 0,
      "call_iv": 0.335944140625,
      "put_iv": 0,
      "call_bid": 0,
      "put_bid": 0,
      "call_ask": 0.01,
      "put_ask": 0,
      "call_last": 0.02,
      "put_last": 0,
      "call_gex": 14248,
      "put_gex": 0,
      "total_gex": 14248,
      "volume": 22,
      "probability": 1.67
    },
    {
      "strike": 759,
      "call_symbol": "QQQ260714C00759000",
      "put_symbol": "",
      "call_oi": 75,
      "put_oi": 0,
      "call_volume": 50,
      "put_volume": 0,
      "call_iv": 0.3437565625,
      "put_iv": 0,
      "call_bid": 0,
      "put_bid": 0,
      "call_ask": 0.01,
      "put_ask": 0,
      "call_last": 0.01,
      "put_last": 0,
      "call_gex": 6727,
      "put_gex": 0,
      "total_gex": 6727,
      "volume": 50,
      "probability": 1.61
    },
    {
      "strike": 760,
      "call_symbol": "QQQ260714C00760000",
      "put_symbol": "QQQ260714P00760000",
      "call_oi": 605,
      "put_oi": 13,
      "call_volume": 1,
      "put_volume": 47,
      "call_iv": 0.35156898437499995,
      "put_iv": 1.0012256970214843,
      "call_bid": 0,
      "put_bid": 39.75,
      "call_ask": 0.01,
      "put_ask": 43.49,
      "call_last": 0.01,
      "put_last": 48.07,
      "call_gex": 555481,
      "put_gex": -11936,
      "total_gex": 543545,
      "volume": 48,
      "probability": 32.51
    },
    {
      "strike": 761,
      "call_symbol": "QQQ260714C00761000",
      "put_symbol": "",
      "call_oi": 2,
      "put_oi": 0,
      "call_volume": 2,
      "put_volume": 0,
      "call_iv": 0.35938140625,
      "put_iv": 0,
      "call_bid": 0,
      "put_bid": 0,
      "call_ask": 0.01,
      "put_ask": 0,
      "call_last": 0.24,
      "put_last": 0,
      "call_gex": 161,
      "put_gex": 0,
      "total_gex": 161,
      "volume": 2,
      "probability": 1.51
    },
    {
      "strike": 762,
      "call_symbol": "QQQ260714C00762000",
      "put_symbol": "",
      "call_oi": 96,
      "put_oi": 0,
      "call_volume": 46,
      "put_volume": 0,
      "call_iv": 0.367193828125,
      "put_iv": 0,
      "call_bid": 0,
      "put_bid": 0,
      "call_ask": 0.01,
      "put_ask": 0,
      "call_last": 0.01,
      "put_last": 0,
      "call_gex": 7330,
      "put_gex": 0,
      "total_gex": 7330,
      "volume": 46,
      "probability": 1.47
    },
    {
      "strike": 763,
      "call_symbol": "QQQ260714C00763000",
      "put_symbol": "",
      "call_oi": 136,
      "put_oi": 0,
      "call_volume": 25,
      "put_volume": 0,
      "call_iv": 0.37500625,
      "put_iv": 0,
      "call_bid": 0,
      "put_bid": 0,
      "call_ask": 0.01,
      "put_ask": 0,
      "call_last": 0.04,
      "put_last": 0,
      "call_gex": 9874,
      "put_gex": 0,
      "total_gex": 9874,
      "volume": 25,
      "probability": 1.43
    },
    {
      "strike": 764,
      "call_symbol": "QQQ260714C00764000",
      "put_symbol": "",
      "call_oi": 37,
      "put_oi": 0,
      "call_volume": 25,
      "put_volume": 0,
      "call_iv": 0.38281867187499996,
      "put_iv": 0,
      "call_bid": 0,
      "put_bid": 0,
      "call_ask": 0.01,
      "put_ask": 0,
      "call_last": 0.02,
      "put_last": 0,
      "call_gex": 2558,
      "put_gex": 0,
      "total_gex": 2558,
      "volume": 25,
      "probability": 1.39
    },
    {
      "strike": 765,
      "call_symbol": "QQQ260714C00765000",
      "put_symbol": "",
      "call_oi": 179,
      "put_oi": 0,
      "call_volume": 102,
      "put_volume": 0,
      "call_iv": 0.39063109375,
      "put_iv": 0,
      "call_bid": 0,
      "put_bid": 0,
      "call_ask": 0.01,
      "put_ask": 0,
      "call_last": 0.01,
      "put_last": 0,
      "call_gex": 11805,
      "put_gex": 0,
      "total_gex": 11805,
      "volume": 102,
      "probability": 1.35
    },
    {
      "strike": 766,
      "call_symbol": "QQQ260714C00766000",
      "put_symbol": "",
      "call_oi": 8,
      "put_oi": 0,
      "call_volume": 1,
      "put_volume": 0,
      "call_iv": 0.398443515625,
      "put_iv": 0,
      "call_bid": 0,
      "put_bid": 0,
      "call_ask": 0.01,
      "put_ask": 0,
      "call_last": 0.12,
      "put_last": 0,
      "call_gex": 504,
      "put_gex": 0,
      "total_gex": 504,
      "volume": 1,
      "probability": 1.31
    },
    {
      "strike": 767,
      "call_symbol": "QQQ260714C00767000",
      "put_symbol": "",
      "call_oi": 603,
      "put_oi": 0,
      "call_volume": 71,
      "put_volume": 0,
      "call_iv": 0.4062559375,
      "put_iv": 0,
      "call_bid": 0,
      "put_bid": 0,
      "call_ask": 0.01,
      "put_ask": 0,
      "call_last": 0.01,
      "put_last": 0,
      "call_gex": 36323,
      "put_gex": 0,
      "total_gex": 36323,
      "volume": 71,
      "probability": 1.28
    },
    {
      "strike": 768,
      "call_symbol": "QQQ260714C00768000",
      "put_symbol": "",
      "call_oi": 96,
      "put_oi": 0,
      "call_volume": 4,
      "put_volume": 0,
      "call_iv": 0.414068359375,
      "put_iv": 0,
      "call_bid": 0,
      "put_bid": 0,
      "call_ask": 0.01,
      "put_ask": 0,
      "call_last": 0.01,
      "put_last": 0,
      "call_gex": 5537,
      "put_gex": 0,
      "total_gex": 5537,
      "volume": 4,
      "probability": 1.25
    },
    {
      "strike": 769,
      "call_symbol": "QQQ260714C00769000",
      "put_symbol": "",
      "call_oi": 60,
      "put_oi": 0,
      "call_volume": 0,
      "put_volume": 0,
      "call_iv": 0.42188078125,
      "put_iv": 0,
      "call_bid": 0,
      "put_bid": 0,
      "call_ask": 0.01,
      "put_ask": 0,
      "call_last": 0.02,
      "put_last": 0,
      "call_gex": 3318,
      "put_gex": 0,
      "total_gex": 3318,
      "volume": 0,
      "probability": 1.22
    },
    {
      "strike": 770,
      "call_symbol": "QQQ260714C00770000",
      "put_symbol": "",
      "call_oi": 406,
      "put_oi": 0,
      "call_volume": 10,
      "put_volume": 0,
      "call_iv": 0.42969320312500003,
      "put_iv": 0,
      "call_bid": 0,
      "put_bid": 0,
      "call_ask": 0.01,
      "put_ask": 0,
      "call_last": 0.02,
      "put_last": 0,
      "call_gex": 21547,
      "put_gex": 0,
      "total_gex": 21547,
      "volume": 10,
      "probability": 1.19
    },
    {
      "strike": 771,
      "call_symbol": "QQQ260714C00771000",
      "put_symbol": "",
      "call_oi": 21,
      "put_oi": 0,
      "call_volume": 1,
      "put_volume": 0,
      "call_iv": 0.437505625,
      "put_iv": 0,
      "call_bid": 0,
      "put_bid": 0,
      "call_ask": 0.01,
      "put_ask": 0,
      "call_last": 0.01,
      "put_last": 0,
      "call_gex": 1071,
      "put_gex": 0,
      "total_gex": 1071,
      "volume": 1,
      "probability": 1.17
    },
    {
      "strike": 772,
      "call_symbol": "QQQ260714C00772000",
      "put_symbol": "",
      "call_oi": 60,
      "put_oi": 0,
      "call_volume": 20,
      "put_volume": 0,
      "call_iv": 0.445318046875,
      "put_iv": 0,
      "call_bid": 0,
      "put_bid": 0,
      "call_ask": 0.01,
      "put_ask": 0,
      "call_last": 0.02,
      "put_last": 0,
      "call_gex": 2943,
      "put_gex": 0,
      "total_gex": 2943,
      "volume": 20,
      "probability": 1.14
    },
    {
      "strike": 773,
      "call_symbol": "QQQ260714C00773000",
      "put_symbol": "",
      "call_oi": 989,
      "put_oi": 0,
      "call_volume": 10,
      "put_volume": 0,
      "call_iv": 0.45313046875,
      "put_iv": 0,
      "call_bid": 0,
      "put_bid": 0,
      "call_ask": 0.01,
      "put_ask": 0,
      "call_last": 0.01,
      "put_last": 0,
      "call_gex": 46700,
      "put_gex": 0,
      "total_gex": 46700,
      "volume": 10,
      "probability": 1.12
    },
    {
      "strike": 774,
      "call_symbol": "QQQ260714C00774000",
      "put_symbol": "",
      "call_oi": 60,
      "put_oi": 0,
      "call_volume": 20,
      "put_volume": 0,
      "call_iv": 0.46094289062500005,
      "put_iv": 0,
      "call_bid": 0,
      "put_bid": 0,
      "call_ask": 0.01,
      "put_ask": 0,
      "call_last": 0.02,
      "put_last": 0,
      "call_gex": 2730,
      "put_gex": 0,
      "total_gex": 2730,
      "volume": 20,
      "probability": 1.1
    },
    {
      "strike": 775,
      "call_symbol": "QQQ260714C00775000",
      "put_symbol": "",
      "call_oi": 119,
      "put_oi": 0,
      "call_volume": 2,
      "put_volume": 0,
      "call_iv": 0.4687553125,
      "put_iv": 0,
      "call_bid": 0,
      "put_bid": 0,
      "call_ask": 0.01,
      "put_ask": 0,
      "call_last": 0.01,
      "put_last": 0,
      "call_gex": 5223,
      "put_gex": 0,
      "total_gex": 5223,
      "volume": 2,
      "probability": 1.08
    },
    {
      "strike": 780,
      "call_symbol": "QQQ260714C00780000",
      "put_symbol": "",
      "call_oi": 532,
      "put_oi": 0,
      "call_volume": 1,
      "put_volume": 0,
      "call_iv": 0.507817421875,
      "put_iv": 0,
      "call_bid": 0,
      "put_bid": 0,
      "call_ask": 0.01,
      "put_ask": 0,
      "call_last": 0.01,
      "put_last": 0,
      "call_gex": 19739,
      "put_gex": 0,
      "total_gex": 19739,
      "volume": 1,
      "probability": 0.99
    },
    {
      "strike": 785,
      "call_symbol": "QQQ260714C00785000",
      "put_symbol": "",
      "call_oi": 206,
      "put_oi": 0,
      "call_volume": 2,
      "put_volume": 0,
      "call_iv": 0.51562984375,
      "put_iv": 0,
      "call_bid": 0,
      "put_bid": 0,
      "call_ask": 0.01,
      "put_ask": 0,
      "call_last": 0.01,
      "put_last": 0,
      "call_gex": 3881,
      "put_gex": 0,
      "total_gex": 3881,
      "volume": 2,
      "probability": 0.51
    },
    {
      "strike": 790,
      "call_symbol": "QQQ260714C00790000",
      "put_symbol": "",
      "call_oi": 4,
      "put_oi": 0,
      "call_volume": 4,
      "put_volume": 0,
      "call_iv": 0.5468795312500001,
      "put_iv": 0,
      "call_bid": 0,
      "put_bid": 0,
      "call_ask": 0.01,
      "put_ask": 0,
      "call_last": 0.05,
      "put_last": 0,
      "call_gex": 59,
      "put_gex": 0,
      "total_gex": 59,
      "volume": 4,
      "probability": 0.42
    },
    {
      "strike": 795,
      "call_symbol": "QQQ260714C00795000",
      "put_symbol": "",
      "call_oi": 10,
      "put_oi": 0,
      "call_volume": 20,
      "put_volume": 0,
      "call_iv": 0.57812921875,
      "put_iv": 0,
      "call_bid": 0,
      "put_bid": 0,
      "call_ask": 0.01,
      "put_ask": 0,
      "call_last": 0.02,
      "put_last": 0,
      "call_gex": 118,
      "put_gex": 0,
      "total_gex": 118,
      "volume": 20,
      "probability": 0.36
    },
    {
      "strike": 800,
      "call_symbol": "QQQ260714C00800000",
      "put_symbol": "",
      "call_oi": 6,
      "put_oi": 0,
      "call_volume": 1,
      "put_volume": 0,
      "call_iv": 0.6562534375000001,
      "put_iv": 0,
      "call_bid": 0,
      "put_bid": 0,
      "call_ask": 0.01,
      "put_ask": 0,
      "call_last": 0.01,
      "put_last": 0,
      "call_gex": 119,
      "put_gex": 0,
      "total_gex": 119,
      "volume": 1,
      "probability": 0.68
    },
    {
      "strike": 805,
      "call_symbol": "QQQ260714C00805000",
      "put_symbol": "",
      "call_oi": 1,
      "put_oi": 0,
      "call_volume": 0,
      "put_volume": 0,
      "call_iv": 0.6875031250000001,
      "put_iv": 0,
      "call_bid": 0,
      "put_bid": 0,
      "call_ask": 0.01,
      "put_ask": 0,
      "call_last": 0.02,
      "put_last": 0,
      "call_gex": 16,
      "put_gex": 0,
      "total_gex": 16,
      "volume": 0,
      "probability": 0.58
    },
    {
      "strike": 810,
      "call_symbol": "QQQ260714C00810000",
      "put_symbol": "",
      "call_oi": 40,
      "put_oi": 0,
      "call_volume": 20,
      "put_volume": 0,
      "call_iv": 0.6875031250000001,
      "put_iv": 0,
      "call_bid": 0,
      "put_bid": 0,
      "call_ask": 0.01,
      "put_ask": 0,
      "call_last": 0.03,
      "put_last": 0,
      "call_gex": 343,
      "put_gex": 0,
      "total_gex": 343,
      "volume": 20,
      "probability": 0.31
    },
    {
      "strike": 845,
      "call_symbol": "QQQ260714C00845000",
      "put_symbol": "",
      "call_oi": 2,
      "put_oi": 0,
      "call_volume": 0,
      "put_volume": 0,
      "call_iv": 0.9687503125,
      "put_iv": 0,
      "call_bid": 0,
      "put_bid": 0,
      "call_ask": 0.01,
      "put_ask": 0,
      "call_last": 0.01,
      "put_last": 0,
      "call_gex": 14,
      "put_gex": 0,
      "total_gex": 14,
      "volume": 0,
      "probability": 0.34
    },
    {
      "strike": 880,
      "call_symbol": "QQQ260714C00880000",
      "put_symbol": "",
      "call_oi": 12,
      "put_oi": 0,
      "call_volume": 0,
      "put_volume": 0,
      "call_iv": 1.1875040625,
      "put_iv": 0,
      "call_bid": 0,
      "put_bid": 0,
      "call_ask": 0.01,
      "put_ask": 0,
      "call_last": 0.01,
      "put_last": 0,
      "call_gex": 38,
      "put_gex": 0,
      "total_gex": 38,
      "volume": 0,
      "probability": 0.2
    }
  ]
}
